iwp3tb/__init__.py
iwp3tb/ancestors.py
iwp3tb/multiton.py
test/__init__.py
test/test_ancestors.py
test/test_multiton.py
test/testpack/__init__.py
test/testpack/testmod.py
test/testpack/anotherpack/__init__.py
test/testpack/anotherpack/anothermod.py
iwp3tb-0.0.1.dist-info/LICENSE
iwp3tb-0.0.1.dist-info/METADATA
iwp3tb-0.0.1.dist-info/WHEEL
iwp3tb-0.0.1.dist-info/top_level.txt
iwp3tb-0.0.1.dist-info/RECORD
