Metadata-Version: 2.1
Name: iwp3tb
Version: 0.0.1
Summary: Ish West Python 3 Toolbox
Home-page: https://github.com/optimistiCli/ishwest_py3_toolbox
Author: Ish West
Author-email: optimistcli@yandex.kz
License: UNKNOWN
Platform: UNKNOWN
Classifier: Programming Language :: Python :: 3
Classifier: License :: OSI Approved :: MIT License
Classifier: Operating System :: OS Independent
Requires-Python: >=3.7
